{
  "publicPath": "/_nuxt/",
  "all": [
    "../server/index.spa.html",
    "../server/index.ssr.html",
    "07a9dd7.js",
    "0fcf2ff.js",
    "179fa92.js",
    "2400d6f.js",
    "3312db4.js",
    "33ec92f.js",
    "35a9580.js",
    "3c149b9.js",
    "50c10ef.js",
    "54bbc0d.js",
    "69af3bc.js",
    "6cee292.js",
    "6e5b5c2.js",
    "7839f81.js",
    "7ce6239.js",
    "819f9b0.js",
    "9727ce8.js",
    "9904ec8.js",
    "LICENSES",
    "a1c32eb.js",
    "a22f4af.js",
    "c9f7aec.js",
    "cb0db20.js",
    "d0320c1.js",
    "d89b4b9.js",
    "f2f2a21.js",
    "f8f916f.js"
  ],
  "initial": [
    "3c149b9.js",
    "f2f2a21.js",
    "2400d6f.js",
    "7ce6239.js"
  ],
  "async": [
    "07a9dd7.js",
    "0fcf2ff.js",
    "179fa92.js",
    "3312db4.js",
    "33ec92f.js",
    "35a9580.js",
    "50c10ef.js",
    "54bbc0d.js",
    "69af3bc.js",
    "6cee292.js",
    "6e5b5c2.js",
    "7839f81.js",
    "819f9b0.js",
    "9727ce8.js",
    "9904ec8.js",
    "a1c32eb.js",
    "a22f4af.js",
    "c9f7aec.js",
    "cb0db20.js",
    "d0320c1.js",
    "d89b4b9.js",
    "f8f916f.js"
  ],
  "modules": {
    "18604296": [
      27
    ],
    "24708144": [
      12
    ],
    "26127807": [
      15
    ],
    "32496220": [
      7
    ],
    "43996856": [
      27
    ],
    "44092564": [
      27
    ],
    "57657406": [
      27
    ],
    "61070733": [
      27
    ],
    "64194198": [
      27
    ],
    "66276162": [
      27
    ],
    "74002240": [
      18
    ],
    "76971234": [
      27
    ],
    "3ac355ee": [
      16
    ],
    "5ef74ef1": [
      27
    ],
    "74db05d4": [
      27
    ],
    "a6872b12": [
      27
    ],
    "4f7b2bfe": [
      27
    ],
    "53e5b5ae": [
      27
    ],
    "252c5b30": [
      27
    ],
    "1931dc25": [
      27
    ],
    "305774f6": [
      27
    ],
    "e83a2a94": [
      27
    ],
    "6309f187": [
      27
    ],
    "4928db98": [
      5
    ],
    "3d0548ca": [
      27
    ],
    "9ccb08f4": [
      27
    ],
    "498367ba": [
      27
    ],
    "17cae7a3": [
      5
    ],
    "75d41eee": [
      27
    ],
    "78667d28": [
      27
    ],
    "072bcace": [
      5
    ],
    "5eb9b365": [
      5
    ],
    "4853a7c4": [
      27
    ],
    "9a808e62": [
      27
    ],
    "d7a51888": [
      27
    ],
    "5798654c": [
      27
    ],
    "5fbbc540": [
      27
    ],
    "3825729f": [
      27
    ],
    "d9d85908": [
      27
    ],
    "15c20804": [
      27
    ],
    "6c491824": [
      5
    ],
    "11c9cc92": [
      27
    ],
    "15e73e2d": [
      16
    ],
    "3d82f674": [
      16
    ],
    "280c6232": [
      16
    ],
    "553ca974": [
      16
    ],
    "0863ccd4": [
      16
    ],
    "7ae5149e": [
      16
    ],
    "758c3fbe": [
      16
    ],
    "10aaeae6": [
      16
    ],
    "6dd97c3b": [
      16
    ],
    "4429e28f": [
      16
    ],
    "87b21772": [
      16
    ],
    "79faeefa": [
      16
    ],
    "14cd625b": [
      16
    ],
    "3d1fe2ba": [
      16
    ],
    "21d7943e": [
      16
    ],
    "61aea096": [
      16
    ],
    "105ddbfb": [
      16
    ],
    "0eb216c7": [
      16
    ],
    "541e0748": [
      16
    ],
    "69de73e9": [
      16
    ],
    "8cc72bce": [
      16
    ],
    "bee4266c": [
      16
    ],
    "0fbb9d8b": [
      27
    ],
    "3ac5bfa4": [
      27
    ],
    "408aa501": [
      27
    ],
    "108374ac": [
      27
    ],
    "2b7256c0": [
      27
    ],
    "351376cb": [
      27
    ],
    "885db502": [
      27
    ],
    "7f575ded": [
      27
    ],
    "4e96571c": [
      27
    ],
    "202be9a4": [
      27
    ],
    "7b533a4b": [
      27
    ],
    "55d5ab33": [
      27
    ],
    "c0a98aac": [
      27
    ],
    "1dfb4697": [
      27
    ],
    "c8476dd6": [
      27
    ],
    "30f5a6c0": [
      27
    ],
    "59c44588": [
      27
    ],
    "f2b7b0f0": [
      27
    ],
    "3c186d58": [
      27
    ],
    "774c69d8": [
      27
    ],
    "924796de": [
      27
    ],
    "ae248f62": [
      27
    ],
    "a23bea26": [
      27
    ],
    "74376e95": [
      27
    ],
    "5bd090aa": [
      27
    ],
    "df7691a2": [
      27
    ],
    "1994cb80": [
      27
    ],
    "fe792eaa": [
      27
    ],
    "4718e96f": [
      27
    ],
    "6ad42533": [
      27
    ],
    "36d92b8c": [
      27
    ],
    "01d71b01": [
      27
    ],
    "54668bf9": [
      5
    ],
    "96f33d5c": [
      27
    ],
    "deb4cf0e": [
      27
    ],
    "b8df56e4": [
      27
    ],
    "4eacf2f2": [
      27
    ],
    "45d0341c": [
      27
    ],
    "406593b8": [
      27
    ],
    "7646e9a9": [
      27
    ],
    "16ee63ad": [
      27
    ],
    "7616f757": [
      27
    ],
    "6318bada": [
      27
    ],
    "bc14786e": [
      27
    ],
    "7979d524": [
      27
    ],
    "e0977822": [
      27
    ],
    "878f855c": [
      27
    ],
    "f090317a": [
      27
    ],
    "00870e9c": [
      27
    ],
    "46c8b239": [
      27
    ],
    "b47c1910": [
      27
    ],
    "320e3ba1": [
      27
    ],
    "0c388042": [
      5
    ],
    "6963993f": [
      5
    ],
    "fdd7e574": [
      5
    ],
    "0d64dabb": [
      27
    ],
    "99d218ac": [
      27
    ],
    "b3d0cf9a": [
      27
    ],
    "69cbdd39": [
      27
    ],
    "762af584": [
      27
    ],
    "43902b4c": [
      27
    ],
    "43c22864": [
      27
    ],
    "4a6840c8": [
      27
    ],
    "ef69400c": [
      27
    ],
    "3b3a0998": [
      27
    ],
    "7ff235ee": [
      27
    ],
    "2b46e14c": [
      27
    ],
    "0b2217cf": [
      27
    ],
    "74c85780": [
      27
    ],
    "2fed48ce": [
      27
    ],
    "61af8a24": [
      27
    ],
    "44e43504": [
      27
    ],
    "6596dbdf": [
      27
    ],
    "70adc44b": [
      27
    ],
    "19be1a20": [
      5
    ],
    "7eec95f2": [
      5
    ],
    "007e2c4b": [
      5
    ],
    "10049a0e": [
      5
    ],
    "734b79c6": [
      5
    ],
    "c8ca1034": [
      5
    ],
    "599797e4": [
      16
    ],
    "d3664648": [
      27
    ],
    "7fcfc78f": [
      27
    ],
    "1db03616": [
      27
    ],
    "1d449c8c": [
      27
    ],
    "0819a150": [
      27
    ],
    "b0ee7520": [
      27
    ],
    "7e07ed70": [
      27
    ],
    "2a35fab1": [
      27
    ],
    "0614e63c": [
      27
    ],
    "be1bbc24": [
      27
    ],
    "0a35dcbe": [
      27
    ],
    "7485409e": [
      27
    ],
    "2f281a00": [
      27
    ],
    "8a076752": [
      27
    ],
    "4e1a241b": [
      27
    ],
    "4255f316": [
      27
    ],
    "26dd08f0": [
      27
    ],
    "c66ec500": [
      27
    ],
    "2c2a8be6": [
      27
    ],
    "58642a64": [
      27
    ],
    "64ddb2d8": [
      27
    ],
    "16fd3904": [
      27
    ],
    "3b792ed4": [
      27
    ],
    "6e36fa4f": [
      27
    ],
    "e6ac9810": [
      27
    ],
    "c205792c": [
      27
    ],
    "2e80c428": [
      27
    ],
    "2bce1f84": [
      27
    ],
    "96953e3a": [
      16
    ],
    "a276dd2e": [
      16
    ],
    "efaf3a38": [
      16
    ],
    "d864f98a": [
      16
    ],
    "1f4aefd2": [
      16
    ],
    "309e55dd": [
      16
    ],
    "6fe5e66a": [
      5
    ],
    "2b9d8425": [
      27
    ],
    "8d8e7348": [
      5
    ],
    "00888d6e": [
      5
    ],
    "6021b145": [
      27
    ],
    "29428a64": [
      27
    ],
    "979f979e": [
      27
    ],
    "6f878070": [
      27
    ],
    "31ff853d": [
      27
    ],
    "b583a1f4": [
      27
    ],
    "335e371a": [
      27
    ],
    "06151445": [
      27
    ],
    "e0cb8b62": [
      27
    ],
    "2f6f7f54": [
      27
    ],
    "14662e8b": [
      27
    ],
    "3aa3b42c": [
      27
    ],
    "4df24021": [
      27
    ],
    "fe3025c4": [
      27
    ],
    "1c3c15d0": [
      27
    ],
    "e3ddfa00": [
      27
    ],
    "248a5dc1": [
      27
    ],
    "1f7f1a7e": [
      27
    ],
    "0729a858": [
      27
    ],
    "3652b3bc": [
      27
    ],
    "885192a8": [
      27
    ],
    "45e1deae": [
      27
    ],
    "0a8ba30f": [
      27
    ],
    "45aa33c9": [
      27
    ],
    "57beaeb0": [
      27
    ],
    "75b0db3e": [
      27
    ],
    "8af65f40": [
      27
    ],
    "01df5302": [
      27
    ],
    "5a9b98dc": [
      27
    ],
    "69a4edfc": [
      27
    ],
    "6fc39078": [
      27
    ],
    "2c4fa26f": [
      27
    ],
    "1f78d6ce": [
      27
    ],
    "8c23a106": [
      27
    ],
    "161ea080": [
      27
    ],
    "f88214de": [
      27
    ],
    "665f3df4": [
      27
    ],
    "21a09c5a": [
      27
    ],
    "a6bac49a": [
      27
    ],
    "648c9ad1": [
      27
    ],
    "ec316d76": [
      27
    ],
    "14eefcb9": [
      27
    ],
    "ee6d3b04": [
      27
    ],
    "19d61351": [
      27
    ],
    "86f17460": [
      27
    ],
    "c0ef972a": [
      27
    ],
    "c1cbaf9a": [
      27
    ],
    "3a421cfd": [
      16
    ],
    "df789550": [
      16
    ],
    "79c5fa06": [
      16
    ],
    "2398c995": [
      5
    ],
    "a6d1e23c": [
      5
    ],
    "56d12ede": [
      5
    ],
    "d373b89a": [
      27
    ],
    "d76b40ec": [
      5
    ],
    "d8fa46d4": [
      16
    ],
    "31b2d317": [
      27
    ],
    "375ae5ca": [
      27
    ],
    "54b398b6": [
      16
    ],
    "f7a1047a": [
      5
    ],
    "65b4c104": [
      16
    ],
    "fc82002e": [
      27
    ],
    "140c3fc4": [
      27
    ],
    "ea248c28": [
      27
    ],
    "35b3b783": [
      27
    ],
    "091d30b3": [
      27
    ],
    "5f1de5c0": [
      27
    ],
    "7fbcf7db": [
      27
    ],
    "0ff87162": [
      27
    ],
    "0d98a1bb": [
      27
    ],
    "46a44b20": [
      27
    ],
    "6ec4b572": [
      27
    ],
    "8d87f96e": [
      27
    ],
    "bb1969f4": [
      27
    ],
    "5229bb70": [
      27
    ],
    "6319426e": [
      27
    ],
    "41da1b26": [
      27
    ],
    "7e3bcdc6": [
      27
    ],
    "c29bff50": [
      27
    ],
    "269746a8": [
      27
    ],
    "9bfcd3b4": [
      27
    ],
    "0177a494": [
      27
    ],
    "0ad6ebb3": [
      27
    ],
    "7abc0e74": [
      27
    ],
    "04b45065": [
      27
    ],
    "e46d7fda": [
      27
    ],
    "c257035a": [
      27
    ],
    "922fcb68": [
      27
    ],
    "3fbff0a6": [
      27
    ],
    "27dce4c7": [
      27
    ],
    "b01441f0": [
      27
    ],
    "4d09faf0": [
      27
    ],
    "72ccf3de": [
      27
    ],
    "5bc296f6": [
      27
    ],
    "d6420996": [
      27
    ],
    "27b9fe55": [
      27
    ],
    "18fc8cc7": [
      27
    ],
    "d7f8cc3c": [
      27
    ],
    "a9884706": [
      27
    ],
    "4027b1d2": [
      27
    ],
    "b262dde8": [
      27
    ],
    "39db93ec": [
      27
    ],
    "b2c79e48": [
      27
    ],
    "6a603fb7": [
      27
    ],
    "52b01914": [
      27
    ],
    "979cddfa": [
      27
    ],
    "4f70149f": [
      27
    ],
    "5268825c": [
      27
    ],
    "64db3111": [
      27
    ],
    "4921aaca": [
      27
    ],
    "0edcc2e4": [
      27
    ],
    "3dc8dfa2": [
      27
    ],
    "84fc403a": [
      27
    ],
    "670441b2": [
      27
    ],
    "1c5ac0e0": [
      27
    ],
    "6e048e93": [
      27
    ],
    "6dda725a": [
      27
    ],
    "37ff085b": [
      27
    ],
    "cd1e8a76": [
      27
    ],
    "6be87b39": [
      27
    ],
    "00a723a2": [
      27
    ],
    "e5d65216": [
      27
    ],
    "5ac65b5a": [
      27
    ],
    "46bc06c3": [
      27
    ],
    "9b093466": [
      27
    ],
    "19699c41": [
      16
    ],
    "15dc116d": [
      16
    ],
    "4388739c": [
      16
    ],
    "259b6470": [
      16
    ],
    "7ace5f34": [
      5
    ],
    "c781d678": [
      5
    ],
    "4ff26c06": [
      27
    ],
    "1a0bf17e": [
      16
    ],
    "fb4e7926": [
      16
    ],
    "17c244b7": [
      16
    ],
    "b635eac8": [
      2
    ],
    "cd8e2c12": [
      14
    ],
    "351dee05": [
      13
    ],
    "6ae9cd22": [
      21
    ],
    "1217446c": [
      7
    ],
    "3a5b2e8a": [
      3
    ],
    "bca00024": [
      22
    ],
    "c085b26a": [
      24
    ],
    "00d4941d": [
      23
    ],
    "2ced71e4": [
      12
    ],
    "4d79fd2c": [
      17
    ],
    "029c6c5a": [
      15
    ],
    "76bef81c": [
      11
    ],
    "4b809008": [
      8
    ],
    "06ee92d8": [
      2
    ],
    "65fa6fa8": [
      2
    ],
    "097b1b9a": [
      14
    ],
    "7d52b0f2": [
      14
    ],
    "7b6ae83f": [
      13
    ],
    "98fda3a6": [
      13
    ],
    "aeed7374": [
      13
    ],
    "3ae65741": [
      13
    ],
    "667af0d6": [
      13
    ],
    "2c94a1ab": [
      21
    ],
    "1aae5202": [
      21
    ],
    "2c6da00e": [
      7
    ],
    "387a663a": [
      7
    ],
    "12e62064": [
      3
    ],
    "3280dafa": [
      3
    ],
    "51ad7b9c": [
      22
    ],
    "3993ef44": [
      22
    ],
    "55932de2": [
      24
    ],
    "3d79a18a": [
      24
    ],
    "364dd661": [
      23
    ],
    "425a9c8d": [
      23
    ],
    "e2120bc0": [
      12
    ],
    "550b2f74": [
      12
    ],
    "71adf930": [
      17
    ],
    "3cb502bc": [
      17
    ],
    "75784a17": [
      15
    ],
    "f7c3cb7a": [
      15
    ],
    "1f240350": [
      11
    ],
    "65f9fdac": [
      11
    ],
    "e0da7b90": [
      8
    ],
    "1b242d8c": [
      8
    ],
    "65ef8875": [
      10
    ],
    "f53e661c": [
      10
    ],
    "6db3f876": [
      10
    ],
    "2b787fe0": [
      10
    ],
    "6726e270": [
      10
    ],
    "aa7e56fe": [
      2
    ],
    "58e88e0c": [
      2
    ],
    "b9973efc": [
      2
    ],
    "249d887a": [
      2
    ],
    "3620aa54": [
      2
    ],
    "76809fbb": [
      14
    ],
    "563c39db": [
      14
    ],
    "21f49dbc": [
      14
    ],
    "21f13449": [
      14
    ],
    "963e30e4": [
      14
    ],
    "880abb24": [
      13
    ],
    "317a6caf": [
      13
    ],
    "0c7df76f": [
      13
    ],
    "384af8c6": [
      13
    ],
    "d501d67e": [
      13
    ],
    "5f3775e2": [
      21
    ],
    "0ce7047e": [
      21
    ],
    "4c652ee3": [
      21
    ],
    "757d0fa2": [
      21
    ],
    "415d0e96": [
      21
    ],
    "0a70060a": [
      7
    ],
    "21ec36fc": [
      7
    ],
    "579307c2": [
      7
    ],
    "c12cdc2c": [
      7
    ],
    "b28cca40": [
      18
    ],
    "9bd99e1c": [
      18
    ],
    "161839e1": [
      18
    ],
    "74d0d033": [
      18
    ],
    "3604b8be": [
      3
    ],
    "032154d4": [
      3
    ],
    "2459cc82": [
      3
    ],
    "201c21e8": [
      3
    ],
    "0165712d": [
      3
    ],
    "1f843ec1": [
      22
    ],
    "8f94ce40": [
      22
    ],
    "539106c2": [
      22
    ],
    "28ed51b2": [
      22
    ],
    "5de33ca0": [
      22
    ],
    "63f6809a": [
      26
    ],
    "a655a86e": [
      26
    ],
    "bad15498": [
      26
    ],
    "250e7b92": [
      26
    ],
    "56754ef4": [
      26
    ],
    "730b63fc": [
      6
    ],
    "3880a394": [
      6
    ],
    "0e6ea303": [
      6
    ],
    "4d6aae08": [
      6
    ],
    "f26e521e": [
      6
    ],
    "1d67b7b8": [
      24
    ],
    "5332883a": [
      24
    ],
    "53e7b325": [
      24
    ],
    "471e74b5": [
      24
    ],
    "5d35e3da": [
      24
    ],
    "1694553c": [
      23
    ],
    "7fb03d1e": [
      23
    ],
    "55410a63": [
      23
    ],
    "30df9a43": [
      23
    ],
    "5a83355e": [
      23
    ],
    "540d7324": [
      12
    ],
    "0f607742": [
      12
    ],
    "bca37e48": [
      12
    ],
    "e987e39e": [
      12
    ],
    "7be0f0f8": [
      17
    ],
    "61a548c2": [
      17
    ],
    "0febfa85": [
      17
    ],
    "07e4aa30": [
      17
    ],
    "4219fd57": [
      17
    ],
    "6cb65118": [
      15
    ],
    "eedb085a": [
      15
    ],
    "a48f77ce": [
      15
    ],
    "1b8508b6": [
      15
    ],
    "46b0af98": [
      11
    ],
    "9d7f0d4c": [
      11
    ],
    "3d49b2ce": [
      11
    ],
    "577fdac8": [
      11
    ],
    "1389296b": [
      11
    ],
    "6c5d15a7": [
      28
    ],
    "d2fcd3a8": [
      28
    ],
    "47cd8ba8": [
      28
    ],
    "8fa33b04": [
      28
    ],
    "5b5fe316": [
      28
    ],
    "0352d25e": [
      4
    ],
    "4d68a7f2": [
      4
    ],
    "e6899a5c": [
      4
    ],
    "2fc28940": [
      4
    ],
    "4c2b78b8": [
      4
    ],
    "a760123a": [
      8
    ],
    "2025b670": [
      8
    ],
    "f00c0638": [
      8
    ],
    "8a486c44": [
      8
    ],
    "55ade494": [
      8
    ]
  },
  "assetsMapping": {
    "353aa0a7": [
      "07a9dd7.js"
    ],
    "29bd80b0": [
      "0fcf2ff.js"
    ],
    "a51d34de": [
      "179fa92.js"
    ],
    "7ea24c87": [
      "2400d6f.js"
    ],
    "ff2f0328": [
      "3312db4.js"
    ],
    "587c3a36": [
      "33ec92f.js"
    ],
    "7a6a3683": [
      "35a9580.js"
    ],
    "6fca0322": [
      "3c149b9.js"
    ],
    "68e8e61b": [
      "50c10ef.js"
    ],
    "b6ff2384": [
      "54bbc0d.js"
    ],
    "9f08fbf8": [
      "69af3bc.js"
    ],
    "310a54d8": [
      "6cee292.js"
    ],
    "9075ce3e": [
      "6e5b5c2.js"
    ],
    "241d7c82": [
      "7839f81.js"
    ],
    "1a3ae26b": [
      "7ce6239.js"
    ],
    "b6ffc7ac": [
      "819f9b0.js"
    ],
    "73dae606": [
      "9727ce8.js"
    ],
    "48ecd9b5": [
      "9904ec8.js"
    ],
    "70331a88": [
      "a1c32eb.js"
    ],
    "587c10aa": [
      "a22f4af.js"
    ],
    "587bf268": [
      "c9f7aec.js"
    ],
    "587bf2e4": [
      "cb0db20.js"
    ],
    "88cfa6ca": [
      "d0320c1.js"
    ],
    "b702784e": [
      "d89b4b9.js"
    ],
    "085a35c4": [
      "f2f2a21.js"
    ],
    "2a130dde": [
      "f8f916f.js"
    ]
  }
}